arakneed/__init__.py
arakneed/cacher.py
arakneed/crawler.py
arakneed/exceptions.py
arakneed/logger.py
arakneed/scheduler.py
arakneed/shared.py
arakneed/spider.py
arakneed/visitor.py
arakneed-0.3.0.dist-info/LICENSE
arakneed-0.3.0.dist-info/METADATA
arakneed-0.3.0.dist-info/WHEEL
arakneed-0.3.0.dist-info/top_level.txt
arakneed-0.3.0.dist-info/RECORD
