Metadata-Version: 2.1
Name: arakneed
Version: 0.3.0
Summary: A common use targeted concurrent crawler for any directed graph. It's designed to be easy to use.
Home-page: https://github.com/arakneed/crawler
Author: arakneed
Author-email: arakneed@somarl.com
License: MIT
Platform: UNKNOWN
Classifier: Operating System :: OS Independent
Classifier: Programming Language :: Python :: 3.8
Classifier: License :: OSI Approved :: MIT License
License-File: LICENSE
